odoo/addons/website_sale_checkout_skip_payment/README.rst
odoo/addons/website_sale_checkout_skip_payment/__init__.py
odoo/addons/website_sale_checkout_skip_payment/__manifest__.py
odoo/addons/website_sale_checkout_skip_payment/controllers/__init__.py
odoo/addons/website_sale_checkout_skip_payment/controllers/main.py
odoo/addons/website_sale_checkout_skip_payment/i18n/am.po
odoo/addons/website_sale_checkout_skip_payment/i18n/ar.po
odoo/addons/website_sale_checkout_skip_payment/i18n/bg.po
odoo/addons/website_sale_checkout_skip_payment/i18n/bs.po
odoo/addons/website_sale_checkout_skip_payment/i18n/ca.po
odoo/addons/website_sale_checkout_skip_payment/i18n/cs.po
odoo/addons/website_sale_checkout_skip_payment/i18n/da.po
odoo/addons/website_sale_checkout_skip_payment/i18n/de.po
odoo/addons/website_sale_checkout_skip_payment/i18n/el_GR.po
odoo/addons/website_sale_checkout_skip_payment/i18n/en_GB.po
odoo/addons/website_sale_checkout_skip_payment/i18n/es.po
odoo/addons/website_sale_checkout_skip_payment/i18n/es_AR.po
odoo/addons/website_sale_checkout_skip_payment/i18n/es_CL.po
odoo/addons/website_sale_checkout_skip_payment/i18n/es_CO.po
odoo/addons/website_sale_checkout_skip_payment/i18n/es_CR.po
odoo/addons/website_sale_checkout_skip_payment/i18n/es_DO.po
odoo/addons/website_sale_checkout_skip_payment/i18n/es_EC.po
odoo/addons/website_sale_checkout_skip_payment/i18n/es_MX.po
odoo/addons/website_sale_checkout_skip_payment/i18n/es_PE.po
odoo/addons/website_sale_checkout_skip_payment/i18n/es_VE.po
odoo/addons/website_sale_checkout_skip_payment/i18n/et.po
odoo/addons/website_sale_checkout_skip_payment/i18n/eu.po
odoo/addons/website_sale_checkout_skip_payment/i18n/fa.po
odoo/addons/website_sale_checkout_skip_payment/i18n/fi.po
odoo/addons/website_sale_checkout_skip_payment/i18n/fr.po
odoo/addons/website_sale_checkout_skip_payment/i18n/fr_CA.po
odoo/addons/website_sale_checkout_skip_payment/i18n/fr_CH.po
odoo/addons/website_sale_checkout_skip_payment/i18n/gl.po
odoo13_addon_website_sale_checkout_skip_payment-13.0.1.1.1.dist-info/METADATA
odoo13_addon_website_sale_checkout_skip_payment-13.0.1.1.1.dist-info/WHEEL
odoo13_addon_website_sale_checkout_skip_payment-13.0.1.1.1.dist-info/top_level.txt
odoo13_addon_website_sale_checkout_skip_payment-13.0.1.1.1.dist-info/RECORD
